README.md
setup.py
gdk/Binomialdistribution.py
gdk/Gaussiandistribution.py
gdk/Generaldistribution.py
gdk/__init__.py
gdk.egg-info/PKG-INFO
gdk.egg-info/SOURCES.txt
gdk.egg-info/dependency_links.txt
gdk.egg-info/not-zip-safe
gdk.egg-info/top_level.txt