Metadata-Version: 1.0
Name: gdk
Version: 0.1
Summary: Gaussian distributions
Home-page: UNKNOWN
Author: Dinesh Kumar Gnanasekaran
Author-email: dinesh.gna111@gmail.com
License: UNKNOWN
Platform: UNKNOWN
